{
  "system_id": "generic_symbolic_oracle",
  "status": "planned",
  "cards": [
    {
      "id": "oracle_threshold",
      "name": "Threshold",
      "arcana": "symbolic",
      "tags": ["transition", "edge", "choice", "gate"]
    },
    {
      "id": "oracle_mirror",
      "name": "Mirror",
      "arcana": "symbolic",
      "tags": ["reflection", "self_view", "pattern", "recognition"]
    },
    {
      "id": "oracle_seed",
      "name": "Seed",
      "arcana": "symbolic",
      "tags": ["potential", "growth", "patience", "beginning"]
    },
    {
      "id": "oracle_thread",
      "name": "Thread",
      "arcana": "symbolic",
      "tags": ["connection", "continuity", "meaning", "weaving"]
    }
  ]
}

